CONTRIBUTING.rst
HISTORY.rst
LICENSE
MANIFEST.in
README.md
requirements-tests.txt
requirements.txt
setup.cfg
setup.py
grma/__init__.py
grma/grma.py
grma/grma_main.py
grma/main.py
grma/donorsgraph/__init__.py
grma/donorsgraph/build_donors_graph.py
grma/donorsgraph/create_lol.py
grma/match/__init__.py
grma/match/donors_matching.py
grma/match/graph_wrapper.py
grma/match/lol_graph.pyx
grma/match/match.py
grma/utilities/__init__.py
grma/utilities/cutils.pyx
grma/utilities/geno_representation.py
grma/utilities/utils.py
py_graph_match.egg-info/PKG-INFO
py_graph_match.egg-info/SOURCES.txt
py_graph_match.egg-info/dependency_links.txt
py_graph_match.egg-info/not-zip-safe
py_graph_match.egg-info/requires.txt
py_graph_match.egg-info/top_level.txt