Metadata-Version: 2.1
Name: py-graph-match
Version: 0.0.8
Summary: Graph Match
Home-page: https://github.com/nmdp-bioinformatics/
Author: Pradeep Bashyal
Author-email: pbashyal@nmdp.org
License: LGPL 3.0
Keywords: Graph,HLA
Classifier: Development Status :: 2 - Pre-Alpha
Classifier: Intended Audience :: Developers
Classifier: License :: OSI Approved :: GNU Lesser General Public License v3 (LGPLv3)
Classifier: Natural Language :: English
Classifier: Programming Language :: Python :: 3.8
Classifier: Programming Language :: Python :: 3.9
Classifier: Programming Language :: Python :: 3.10
Requires-Python: >=3.8
License-File: LICENSE
